pytest_mfd_logging/__init__.py
pytest_mfd_logging/amber_log_filter.py
pytest_mfd_logging/amber_log_formatter.py
pytest_mfd_logging/amber_vars.py
pytest_mfd_logging/exceptions.py
pytest_mfd_logging/marker.py
pytest_mfd_logging/pytest_mfd_logging.py
pytest_mfd_logging/configs/pytest.ini
pytest_mfd_logging/templates/html/base.html
pytest_mfd_logging/templates/html/index.html
pytest_mfd_logging/templates/html/module.html
pytest_mfd_logging/templates/html/normalize.css
pytest_mfd_logging/templates/html/style.css
pytest_mfd_logging/templates/html/test.html
pytest_mfd_logging/templates/html/icons/arrow.svg
pytest_mfd_logging/templates/html/icons/nok.svg
pytest_mfd_logging/templates/html/icons/ok.svg
pytest_mfd_logging/templates/html/icons/skip.svg
pytest_mfd_logging-1.25.1.dist-info/licenses/AUTHORS.md
pytest_mfd_logging-1.25.1.dist-info/licenses/LICENSE.md
pytest_mfd_logging-1.25.1.dist-info/METADATA
pytest_mfd_logging-1.25.1.dist-info/WHEEL
pytest_mfd_logging-1.25.1.dist-info/entry_points.txt
pytest_mfd_logging-1.25.1.dist-info/top_level.txt
pytest_mfd_logging-1.25.1.dist-info/RECORD
