Metadata-Version: 2.4
Name: pytest-mfd-logging
Version: 1.25.1
Summary: Module for handling PyTest logging.
Project-URL: Homepage, https://github.com/intel/mfd
Project-URL: Repository, https://github.com/intel/pytest-mfd-logging
Project-URL: Issues, https://github.com/intel/pytest-mfd-logging/issues
Project-URL: Changelog, https://github.com/intel/pytest-mfd-logging/blob/main/CHANGELOG.md
Classifier: Framework :: Pytest
Requires-Python: <3.14,>=3.10
License-File: LICENSE.md
License-File: AUTHORS.md
Requires-Dist: pytest<9,>=7.2.1
Requires-Dist: pytest-json-report~=1.5
Requires-Dist: pytest-reporter-html1~=0.8
Requires-Dist: ansicolors~=1.1
Requires-Dist: jinja2~=3.1
Requires-Dist: mfd-common-libs<2,>=1.11.0
Dynamic: license-file
